Metadata-Version: 2.1
Name: corporate-finance
Version: 0.0.1
Summary: A comprehensive library for corporate finance in Python
Home-page: https://github.com/harryworlds/corporate-finance
Author: Hemant Thapa
Author-email: hemantthapa1998@gmail.com
License: MIT
Keywords: corporate finance,pandas,yahoo finance,numpy,pandas datareader,seaborn,matplotlib
Classifier: Development Status :: 5 - Production/Stable
Classifier: Intended Audience :: Education
Classifier: Operating System :: Microsoft :: Windows :: Windows 10
Classifier: Operating System :: MacOS :: MacOS X
Classifier: License :: OSI Approved :: MIT License
Classifier: Programming Language :: Python :: 3.6
Classifier: Programming Language :: Python :: 3.7
Classifier: Programming Language :: Python :: 3.8
Classifier: Programming Language :: Python :: 3.9
Classifier: Programming Language :: Python :: 3.10
License-File: LICENCE.txt
